naughty_word_py/__init__.py
naughty_word_py/config.py
naughty_word_py/naughtywords.py
naughty_words_py-1.0.0.dist-info/LICENSE
naughty_words_py-1.0.0.dist-info/METADATA
naughty_words_py-1.0.0.dist-info/WHEEL
naughty_words_py-1.0.0.dist-info/top_level.txt
naughty_words_py-1.0.0.dist-info/RECORD
