Metadata-Version: 2.1
Name: naughty-words-py
Version: 1.0.0
Summary: Naugty words parser for python
Home-page: https://github.com/g0phergit/naughty-words.py
Author: Gopher
Author-email: gopherubuntouch@gmail.com
License: UNKNOWN
Project-URL: Bug Tracker, https://github.com/g0phergit/naughty_words.py/issues
Platform: UNKNOWN
Classifier: Programming Language :: Python :: 3
Classifier: License :: OSI Approved :: GNU General Public License v3 (GPLv3)
Classifier: Operating System :: OS Independent
Classifier: Topic :: Utilities
Requires-Python: >=3.6
License-File: LICENSE
